oremda/meta/__init__.py
oremda/meta/cli.py
oremda-0.0.5.dist-info/entry_points.txt
oremda-0.0.5.dist-info/WHEEL
oremda-0.0.5.dist-info/METADATA
oremda-0.0.5.dist-info/RECORD
